cephdu/__init__.py
cephdu/__main__.py
cephdu-1.0.3.dist-info/LICENSE
cephdu-1.0.3.dist-info/METADATA
cephdu-1.0.3.dist-info/WHEEL
cephdu-1.0.3.dist-info/entry_points.txt
cephdu-1.0.3.dist-info/top_level.txt
cephdu-1.0.3.dist-info/RECORD
